oclk/__init__.py
oclk/__main__.py
oclk/benchmark.py
oclk/benchmark_config.py
oclk/cli.py
oclk/functions.py
oclk/oclk_C.cpython-38-x86_64-linux-gnu.so
oclk/oclk_C.pyi
oclk/oclk_runner.py
oclk/oclk_runner.pyi
oclk/tuner.py
oclk/utils.py
oclk/version.py
oclk/third_party/OpenCL/lib/x86_64/libOpenCL.so
oclk/third_party/OpenCL/lib/x86_64/libOpenCL.so.1
oclk/third_party/OpenCL/lib/x86_64/libOpenCL.so.1.0.0
pyoclk-1.2.3.dist-info/LICENSE
pyoclk-1.2.3.dist-info/METADATA
pyoclk-1.2.3.dist-info/WHEEL
pyoclk-1.2.3.dist-info/top_level.txt
pyoclk-1.2.3.dist-info/RECORD
