Metadata-Version: 2.1
Name: pyoclk
Version: 1.2.3
Summary: An easy way to run OpenCL kernel files
Home-page: https://github.com/jinmingyi1998/opencl_kernels
Download-URL: https://pypi.org/project/pyoclk/
Author: Mingyi Jin
Author-email: jinmingyi1998@sina.cn
License: MIT
Project-URL: Bug Tracker, https://github.com/jinmingyi1998/opencl_kernels/issues
Project-URL: Documentation, https://opencl-kernel-python-wrapper.readthedocs.io/en/latest/
Project-URL: Source Code, https://github.com/jinmingyi1998/opencl_kernels
Classifier: Development Status :: 5 - Production/Stable
Classifier: Environment :: GPU
Classifier: Operating System :: POSIX :: Linux
Classifier: License :: OSI Approved :: MIT License
Classifier: Natural Language :: English
Classifier: Programming Language :: C++
Classifier: Programming Language :: Python :: 3 :: Only
Classifier: Programming Language :: Python :: 3.7
Classifier: Programming Language :: Python :: 3.8
Classifier: Programming Language :: Python :: 3.9
Classifier: Programming Language :: Python :: 3.10
Classifier: Programming Language :: Python :: 3.11
Classifier: Programming Language :: Python :: 3.12
Classifier: Programming Language :: Python :: Implementation :: CPython
Classifier: Topic :: Communications :: Email
Classifier: Topic :: Scientific/Engineering :: Artificial Intelligence
Classifier: Topic :: Scientific/Engineering :: Mathematics
Classifier: Topic :: Scientific/Engineering :: Visualization
Classifier: Topic :: Software Development :: Libraries :: Python Modules
Classifier: Topic :: Utilities
Classifier: Typing :: Typed
Classifier: Intended Audience :: Developers
Requires-Python: >=3.7
License-File: LICENSE
Requires-Dist: numpy
Requires-Dist: pydantic >=2
Requires-Dist: pyyaml
Requires-Dist: tqdm
Requires-Dist: typer
